lanfit_exceptions
