Metadata-Version: 1.1
Name: lanfit-exceptions
Version: 0.1.1
Summary: api exceptions
Home-page: UNKNOWN
Author: ll1l11
Author-email: ll1l11@qq.com
License: MIT
Platform: UNKNOWN
Classifier: Programming Language :: Python :: 3
